backports/__init__.py
backports/asyncio/__init__.py
backports/asyncio/queues/__init__.py
backports/asyncio/queues/compat.py
backports_asyncio_queues-0.1.2.dist-info/METADATA
backports_asyncio_queues-0.1.2.dist-info/WHEEL
backports_asyncio_queues-0.1.2.dist-info/licenses/LICENSE
backports_asyncio_queues-0.1.2.dist-info/RECORD
