Metadata-Version: 2.3
Name: backports.asyncio.queues
Version: 0.1.2
Summary: Backport python 3.13 asyncio Queue with shutdown.
License-File: LICENSE
Requires-Python: >=3.9
